libmidi/__init__.py
libmidi/types/__init__.py
libmidi/types/chunk.py
libmidi/types/event.py
libmidi/types/header.py
libmidi/types/message.py
libmidi/types/messages/__init__.py
libmidi/types/messages/channel.py
libmidi/types/messages/common.py
libmidi/types/messages/meta.py
libmidi/types/messages/system.py
libmidi/types/midifile.py
libmidi/types/track.py
libmidi/utils/__init__.py
libmidi/utils/bytes.py
libmidi/utils/time.py
libmidi/utils/variable_length.py
libmidi-1.1.0.dist-info/WHEEL
libmidi-1.1.0.dist-info/METADATA
libmidi-1.1.0.dist-info/RECORD
