Metadata-Version: 2.1
Name: libmidi
Version: 1.1.0
Summary: MIDI library
Home-page: https://github.com/python-midi/libmidi
License: LGPL-3.0-or-later
Author: Sebastiano Barezzi
Author-email: barezzisebastiano@gmail.com
Requires-Python: >=3.8,<4.0
Classifier: License :: OSI Approved :: GNU Lesser General Public License v3 or later (LGPLv3+)
Classifier: Programming Language :: Python :: 3
Classifier: Programming Language :: Python :: 3.10
Classifier: Programming Language :: Python :: 3.8
Classifier: Programming Language :: Python :: 3.9
Provides-Extra: docs
Requires-Dist: sphinx (>=5.0.1,<6.0.0); extra == "docs"
Requires-Dist: sphinx-rtd-theme (>=1.0.0,<2.0.0); extra == "docs"
Project-URL: Repository, https://github.com/python-midi/libmidi
